Econ/CBSA.py
Econ/DateFormatter.py
Econ/FRED.py
Econ/GDP.py
Econ/Unemployment.py
Econ/__init__.py
Formatter/CBSAFormatter.py
Formatter/DateFormatter.py
Formatter/__init__.py
Federal-1.0.1.dist-info/LICENSE
Federal-1.0.1.dist-info/METADATA
Federal-1.0.1.dist-info/WHEEL
Federal-1.0.1.dist-info/top_level.txt
Federal-1.0.1.dist-info/RECORD
