Metadata-Version: 2.1
Name: Federal
Version: 1.0.1
Summary: A wrapper on to the pandas-datareader package for easier handling of federal reserve (FRED) data
Home-page: https://github.com/Jaseibert/Federal
Author: Jeremy A. Seibert
Author-email: Jaseibert2@eagles.usi.edu
License: UNKNOWN
Platform: UNKNOWN
Classifier: Programming Language :: Python :: 3
Classifier: Programming Language :: Python :: 3.6
Classifier: Programming Language :: Python :: 3.7
Classifier: License :: OSI Approved :: MIT License
Classifier: Operating System :: OS Independent
